{"code":"15782","name":"PR DERMABRASION REGIONAL OTHER THAN FACE","name_source":"hospital_text","needs_curation":true,"code_class":"cpt_cat1","basis_kind":"opps","medicare_national":2967.63,"medicare_basis":"opps","n_hospitals":8,"hospitals":{"utsw_clements":{"gross_charge":null,"cash_price":null,"negotiated":{"min":1081.98,"median":3005.15,"max":4750.0},"posted_spread":{"n_items":0,"gross_min":null,"gross_max":null,"cash_min":null,"cash_max":null},"descriptions":["DERMABRASION REGIONAL OTHER THAN FACE","DERMABRASION OTHER THAN FACE"],"inpatient_fallback":false,"medicare":{"amount":2917.95,"basis":"opps"},"multiples":{"cash_vs_medicare":null,"gross_vs_medicare":null}},"medical_city_dallas":{"gross_charge":null,"cash_price":null,"negotiated":{"min":492.15,"median":2108.69,"max":4332.0},"posted_spread":{"n_items":0,"gross_min":null,"gross_max":null,"cash_min":null,"cash_max":null},"descriptions":["Dermabrasion; regional, other than face"],"inpatient_fallback":false,"medicare":{"amount":2917.95,"basis":"opps"},"multiples":{"cash_vs_medicare":null,"gross_vs_medicare":null}},"thr_harris_methodist_fw":{"gross_charge":null,"cash_price":null,"negotiated":{"min":475.88,"median":3034.67,"max":3297.29},"posted_spread":{"n_items":0,"gross_min":null,"gross_max":null,"cash_min":null,"cash_max":null},"descriptions":["DERMABRASION OTHER THAN FACE"],"inpatient_fallback":false,"medicare":{"amount":2917.95,"basis":"opps"},"multiples":{"cash_vs_medicare":null,"gross_vs_medicare":null}},"ivinson_laramie":{"gross_charge":null,"cash_price":null,"negotiated":{"min":2862.05,"median":2862.05,"max":2862.05},"posted_spread":{"n_items":0,"gross_min":null,"gross_max":null,"cash_min":null,"cash_max":null},"descriptions":["DERMABRASION OTHER THAN FACE"],"inpatient_fallback":false,"medicare":{"amount":2967.63,"basis":"opps"},"multiples":{"cash_vs_medicare":null,"gross_vs_medicare":null}},"regional_west_scottsbluff":{"gross_charge":null,"cash_price":null,"negotiated":{"min":3016.24,"median":3167.05,"max":4524.36},"posted_spread":{"n_items":0,"gross_min":null,"gross_max":null,"cash_min":null,"cash_max":null},"descriptions":["DERMABRASION OTHER THAN FACE"],"inpatient_fallback":false,"medicare":{"amount":3016.24,"basis":"opps"},"multiples":{"cash_vs_medicare":null,"gross_vs_medicare":null}},"cheyenne_regional":{"gross_charge":null,"cash_price":null,"negotiated":{"min":3116.01,"median":3116.01,"max":3116.01},"posted_spread":{"n_items":0,"gross_min":null,"gross_max":null,"cash_min":null,"cash_max":null},"descriptions":["PR DERMABRASION REGIONAL OTHER THAN FACE","DERMABRASION OTHER THAN FACE"],"inpatient_fallback":false,"medicare":{"amount":2967.63,"basis":"opps"},"multiples":{"cash_vs_medicare":null,"gross_vs_medicare":null}},"campbell_county_health":{"gross_charge":null,"cash_price":null,"negotiated":{"min":2575.85,"median":2575.85,"max":2575.85},"posted_spread":{"n_items":0,"gross_min":null,"gross_max":null,"cash_min":null,"cash_max":null},"descriptions":["DERMABRASION OTHER THAN FACE"],"inpatient_fallback":false,"medicare":{"amount":2967.63,"basis":"opps"},"multiples":{"cash_vs_medicare":null,"gross_vs_medicare":null}},"crook_county_sundance":{"gross_charge":null,"cash_price":null,"negotiated":{"min":262.0,"median":262.0,"max":262.0},"posted_spread":{"n_items":0,"gross_min":null,"gross_max":null,"cash_min":null,"cash_max":null},"descriptions":["Dermabrasion other than face"],"inpatient_fallback":false,"medicare":{"amount":2967.63,"basis":"opps"},"multiples":{"cash_vs_medicare":null,"gross_vs_medicare":null}}}}