{"code":"27899","name":"UNLISTED PROCEDURE LEG/ANKLE","name_source":"hospital_text","needs_curation":true,"code_class":"cpt_cat1","basis_kind":"opps","medicare_national":252.01,"medicare_basis":"opps","n_hospitals":12,"hospitals":{"utsw_clements":{"gross_charge":3372.0,"cash_price":1686.0,"negotiated":{"min":239.88,"median":857.38,"max":2967.36},"posted_spread":{"n_items":1,"gross_min":3372.0,"gross_max":3372.0,"cash_min":1686.0,"cash_max":1686.0},"descriptions":["REMOVAL HARDWARE    FROM TIBIA, FIBULA  OR ANKLE","HCHG UNLISTED PROC LEG OR ANKLE","UNLISTED PROCEDURE LEG/ANKLE","ADJUSTMENT OF EXTERNAL FIXATION DEVICE","EXCISION OF SOFT    TISSUE MASS CALF"],"inpatient_fallback":false,"medicare":{"amount":247.79,"basis":"opps"},"multiples":{"cash_vs_medicare":6.8,"gross_vs_medicare":13.6}},"baylor_bumc":{"gross_charge":3914.76,"cash_price":2348.86,"negotiated":{"min":204.89,"median":2544.59,"max":8863.71},"posted_spread":{"n_items":3,"gross_min":3838.28,"gross_max":11363.73,"cash_min":2302.97,"cash_max":6818.24},"descriptions":["HC UNLISTED PROCEDURE LEG/ANKLE","HC LEG/ANKLE SURGERY PR","HC PERCUTANEOUS TENOTOMY W ULTRASOUND, LOWER LEG/ANKLE, SINGLE TENDON"],"inpatient_fallback":false,"medicare":{"amount":247.79,"basis":"opps"},"multiples":{"cash_vs_medicare":9.5,"gross_vs_medicare":15.8}},"medical_city_dallas":{"gross_charge":null,"cash_price":null,"negotiated":{"min":249.03,"median":1995.0,"max":25655.0},"posted_spread":{"n_items":0,"gross_min":null,"gross_max":null,"cash_min":null,"cash_max":null},"descriptions":["Unlisted procedure, leg or ankle"],"inpatient_fallback":false,"medicare":{"amount":247.79,"basis":"opps"},"multiples":{"cash_vs_medicare":null,"gross_vs_medicare":null}},"parkland":{"gross_charge":29445.01,"cash_price":11778.0,"negotiated":{"min":327.77,"median":6154.01,"max":22083.76},"posted_spread":{"n_items":1,"gross_min":29445.01,"gross_max":29445.01,"cash_min":11778.0,"cash_max":11778.0},"descriptions":["Unlisted Procedure Leg/Ankle"],"inpatient_fallback":false,"medicare":{"amount":247.79,"basis":"opps"},"multiples":{"cash_vs_medicare":47.5,"gross_vs_medicare":118.8}},"thr_harris_methodist_fw":{"gross_charge":null,"cash_price":null,"negotiated":{"min":247.79,"median":272.57,"max":1801.89},"posted_spread":{"n_items":0,"gross_min":null,"gross_max":null,"cash_min":null,"cash_max":null},"descriptions":["UNLISTED PX LEG/ANKLE"],"inpatient_fallback":false,"medicare":{"amount":247.79,"basis":"opps"},"multiples":{"cash_vs_medicare":null,"gross_vs_medicare":null}},"ivinson_laramie":{"gross_charge":null,"cash_price":null,"negotiated":{"min":239.88,"median":239.88,"max":239.88},"posted_spread":{"n_items":0,"gross_min":null,"gross_max":null,"cash_min":null,"cash_max":null},"descriptions":["UNLISTED PX LEG/ANKLE"],"inpatient_fallback":false,"medicare":{"amount":252.01,"basis":"opps"},"multiples":{"cash_vs_medicare":null,"gross_vs_medicare":null}},"regional_west_scottsbluff":{"gross_charge":null,"cash_price":null,"negotiated":{"min":256.14,"median":268.94,"max":384.21},"posted_spread":{"n_items":0,"gross_min":null,"gross_max":null,"cash_min":null,"cash_max":null},"descriptions":["UNLISTED PX LEG/ANKLE"],"inpatient_fallback":false,"medicare":{"amount":256.14,"basis":"opps"},"multiples":{"cash_vs_medicare":null,"gross_vs_medicare":null}},"cheyenne_regional":{"gross_charge":null,"cash_price":null,"negotiated":{"min":264.61,"median":264.61,"max":264.61},"posted_spread":{"n_items":0,"gross_min":null,"gross_max":null,"cash_min":null,"cash_max":null},"descriptions":["UNLISTED PX LEG/ANKLE"],"inpatient_fallback":false,"medicare":{"amount":252.01,"basis":"opps"},"multiples":{"cash_vs_medicare":null,"gross_vs_medicare":null}},"banner_casper":{"gross_charge":null,"cash_price":null,"negotiated":{"min":null,"median":null,"max":null},"posted_spread":{"n_items":0,"gross_min":null,"gross_max":null,"cash_min":null,"cash_max":null},"descriptions":["UNLISTED PROCEDURE, LEG OR ANKLE"],"inpatient_fallback":false,"medicare":{"amount":252.01,"basis":"opps"},"multiples":{"cash_vs_medicare":null,"gross_vs_medicare":null}},"campbell_county_health":{"gross_charge":null,"cash_price":null,"negotiated":{"min":215.89,"median":215.89,"max":215.89},"posted_spread":{"n_items":0,"gross_min":null,"gross_max":null,"cash_min":null,"cash_max":null},"descriptions":["UNLISTED PX LEG/ANKLE"],"inpatient_fallback":false,"medicare":{"amount":252.01,"basis":"opps"},"multiples":{"cash_vs_medicare":null,"gross_vs_medicare":null}},"crook_county_sundance":{"gross_charge":null,"cash_price":null,"negotiated":{"min":95.0,"median":95.0,"max":95.0},"posted_spread":{"n_items":0,"gross_min":null,"gross_max":null,"cash_min":null,"cash_max":null},"descriptions":["Leg/ankle surgery procedure"],"inpatient_fallback":false,"medicare":{"amount":252.01,"basis":"opps"},"multiples":{"cash_vs_medicare":null,"gross_vs_medicare":null}},"cody_regional_cody":{"gross_charge":2660.0,"cash_price":2261.0,"negotiated":{"min":1330.0,"median":2420.6,"max":2660.0},"posted_spread":{"n_items":1,"gross_min":2660.0,"gross_max":2660.0,"cash_min":2261.0,"cash_max":2261.0},"descriptions":["Other procedure on leg or ankle"],"inpatient_fallback":false,"medicare":{"amount":252.01,"basis":"opps"},"multiples":{"cash_vs_medicare":9.0,"gross_vs_medicare":10.6}}}}