{"code":"29355","name":"Application of walking cast covering thigh to toe|SERV DELIV PERSONALLY BY PT OR UNDER AN OP PLAN OF CARE","name_source":"hospital_text","needs_curation":true,"code_class":"cpt_cat1","basis_kind":"opps","medicare_national":285.75,"medicare_basis":"opps","n_hospitals":16,"hospitals":{"utsw_clements":{"gross_charge":null,"cash_price":null,"negotiated":{"min":64.78,"median":278.86,"max":2667.0},"posted_spread":{"n_items":0,"gross_min":null,"gross_max":null,"cash_min":null,"cash_max":null},"descriptions":["APPL LONG LEG CAST WALKER","APPLICATION LONG LEG CAST WALKER/AMBULATORY TYPE"],"inpatient_fallback":false,"medicare":{"amount":280.97,"basis":"opps"},"multiples":{"cash_vs_medicare":null,"gross_vs_medicare":null}},"baylor_bumc":{"gross_charge":645.62,"cash_price":387.37,"negotiated":{"min":64.78,"median":322.81,"max":508.41},"posted_spread":{"n_items":1,"gross_min":645.62,"gross_max":645.62,"cash_min":387.37,"cash_max":387.37},"descriptions":["HC CAST LEG LONG W/WALKER AP"],"inpatient_fallback":false,"medicare":{"amount":280.97,"basis":"opps"},"multiples":{"cash_vs_medicare":1.4,"gross_vs_medicare":2.3}},"medical_city_dallas":{"gross_charge":null,"cash_price":null,"negotiated":{"min":63.81,"median":396.595,"max":4332.0},"posted_spread":{"n_items":0,"gross_min":null,"gross_max":null,"cash_min":null,"cash_max":null},"descriptions":["Application of long leg cast (thigh to toes); walker or ambulatory type","Application of long leg cast (thigh to toes); walker or ambulatory type Age 21+","Application of long leg cast (thigh to toes); walker or ambulatory type Age Under 21"],"inpatient_fallback":false,"medicare":{"amount":280.97,"basis":"opps"},"multiples":{"cash_vs_medicare":null,"gross_vs_medicare":null}},"parkland":{"gross_charge":2450.0,"cash_price":980.0,"negotiated":{"min":68.02,"median":780.62,"max":2801.25},"posted_spread":{"n_items":3,"gross_min":2218.11,"gross_max":3735.0,"cash_min":887.24,"cash_max":1494.0},"descriptions":["Application of walking cast covering thigh to toe","Application of walking cast covering thigh to toe|SERV DELIV PERSONALLY BY PT OR UNDER AN OP PLAN OF CARE","Application of walking cast covering thigh to toe|RIGHT SIDE"],"inpatient_fallback":false,"medicare":{"amount":280.97,"basis":"opps"},"multiples":{"cash_vs_medicare":3.5,"gross_vs_medicare":8.7}},"thr_harris_methodist_fw":{"gross_charge":751.5,"cash_price":450.9,"negotiated":{"min":64.78,"median":353.21,"max":1568.0},"posted_spread":{"n_items":1,"gross_min":751.5,"gross_max":751.5,"cash_min":450.9,"cash_max":450.9},"descriptions":["29355 APP OF LONG LEG CAST","APPL LONG LEG CAST WALKER"],"inpatient_fallback":false,"medicare":{"amount":280.97,"basis":"opps"},"multiples":{"cash_vs_medicare":1.6,"gross_vs_medicare":2.7}},"ivinson_laramie":{"gross_charge":null,"cash_price":null,"negotiated":{"min":265.58,"median":265.58,"max":265.58},"posted_spread":{"n_items":0,"gross_min":null,"gross_max":null,"cash_min":null,"cash_max":null},"descriptions":["APPL LONG LEG CAST WALKER"],"inpatient_fallback":false,"medicare":{"amount":285.75,"basis":"opps"},"multiples":{"cash_vs_medicare":null,"gross_vs_medicare":null}},"regional_west_scottsbluff":{"gross_charge":null,"cash_price":null,"negotiated":{"min":290.43,"median":304.95,"max":435.65},"posted_spread":{"n_items":0,"gross_min":null,"gross_max":null,"cash_min":null,"cash_max":null},"descriptions":["PR APPLY LONG LEG CAST,WALKER","APPL LONG LEG CAST WALKER"],"inpatient_fallback":false,"medicare":{"amount":290.43,"basis":"opps"},"multiples":{"cash_vs_medicare":null,"gross_vs_medicare":null}},"cheyenne_regional":{"gross_charge":null,"cash_price":null,"negotiated":{"min":300.04,"median":300.04,"max":300.04},"posted_spread":{"n_items":0,"gross_min":null,"gross_max":null,"cash_min":null,"cash_max":null},"descriptions":["PR APPLICATION LONG LEG CAST WALKER/AMBULATORY TYPE","APPL LONG LEG CAST WALKER"],"inpatient_fallback":false,"medicare":{"amount":285.75,"basis":"opps"},"multiples":{"cash_vs_medicare":null,"gross_vs_medicare":null}},"campbell_county_health":{"gross_charge":null,"cash_price":null,"negotiated":{"min":239.02,"median":239.02,"max":239.02},"posted_spread":{"n_items":0,"gross_min":null,"gross_max":null,"cash_min":null,"cash_max":null},"descriptions":["APPL LONG LEG CAST WALKER"],"inpatient_fallback":false,"medicare":{"amount":285.75,"basis":"opps"},"multiples":{"cash_vs_medicare":null,"gross_vs_medicare":null}},"sublette_county_pinedale":{"gross_charge":447.5,"cash_price":402.75,"negotiated":{"min":94.43,"median":394.875,"max":608.05},"posted_spread":{"n_items":2,"gross_min":254.0,"gross_max":641.0,"cash_min":228.6,"cash_max":576.9},"descriptions":["Application of walking cast covering thigh to toe"],"inpatient_fallback":false,"medicare":{"amount":285.75,"basis":"opps"},"multiples":{"cash_vs_medicare":1.4,"gross_vs_medicare":1.6}},"three_rivers_basin":{"gross_charge":null,"cash_price":null,"negotiated":{"min":null,"median":null,"max":null},"posted_spread":{"n_items":0,"gross_min":null,"gross_max":null,"cash_min":null,"cash_max":null},"descriptions":["29355 Apply Long Leg Cast Walker/Ambulatory Type"],"inpatient_fallback":false,"medicare":{"amount":285.75,"basis":"opps"},"multiples":{"cash_vs_medicare":null,"gross_vs_medicare":null}},"washakie_worland":{"gross_charge":222.0,"cash_price":132.98,"negotiated":{"min":106.56,"median":215.34,"max":326.34},"posted_spread":{"n_items":3,"gross_min":222.0,"gross_max":333.0,"cash_min":132.98,"cash_max":199.47},"descriptions":["PF APPL CAST LEG LONG WALKER BI","PF APPL CAST LEG LONG WALKER LT","PF APPL CAST LEG LONG WALKER RT"],"inpatient_fallback":false,"medicare":{"amount":285.75,"basis":"opps"},"multiples":{"cash_vs_medicare":0.5,"gross_vs_medicare":0.8}},"powell_valley_powell":{"gross_charge":504.7,"cash_price":429.0,"negotiated":{"min":429.0,"median":469.37,"max":479.47},"posted_spread":{"n_items":1,"gross_min":504.7,"gross_max":504.7,"cash_min":429.0,"cash_max":429.0},"descriptions":["APPLY LONG LEG CAST WALKER/AMBULATORY TYPE"],"inpatient_fallback":false,"medicare":{"amount":285.75,"basis":"opps"},"multiples":{"cash_vs_medicare":1.5,"gross_vs_medicare":1.8}},"crook_county_sundance":{"gross_charge":null,"cash_price":null,"negotiated":{"min":95.0,"median":95.0,"max":95.0},"posted_spread":{"n_items":0,"gross_min":null,"gross_max":null,"cash_min":null,"cash_max":null},"descriptions":["Application of long leg cast"],"inpatient_fallback":false,"medicare":{"amount":285.75,"basis":"opps"},"multiples":{"cash_vs_medicare":null,"gross_vs_medicare":null}},"star_valley_afton":{"gross_charge":null,"cash_price":null,"negotiated":{"min":null,"median":null,"max":null},"posted_spread":{"n_items":0,"gross_min":null,"gross_max":null,"cash_min":null,"cash_max":null},"descriptions":["APPLICATION LONG LEG CAST WALKER/AMBULATORY TYPE"],"inpatient_fallback":false,"medicare":{"amount":285.75,"basis":"opps"},"multiples":{"cash_vs_medicare":null,"gross_vs_medicare":null}},"sweetwater_memorial_rock_springs":{"gross_charge":455.0,"cash_price":455.0,"negotiated":{"min":null,"median":null,"max":null},"posted_spread":{"n_items":1,"gross_min":455.0,"gross_max":455.0,"cash_min":455.0,"cash_max":455.0},"descriptions":["Long leg walker cast"],"inpatient_fallback":true,"medicare":{"amount":285.75,"basis":"opps"},"multiples":{"cash_vs_medicare":1.6,"gross_vs_medicare":1.6}}}}