{"code":"31293","name":"NASAL/SINUS ENDOSCOPY, SURGICAL, WITH ORBITAL DECOMPRESSION; MEDIAL AND INFERIOR WALL","name_source":"hospital_text","needs_curation":true,"code_class":"cpt_cat1","basis_kind":"opps","medicare_national":7210.32,"medicare_basis":"opps","n_hospitals":9,"hospitals":{"utsw_clements":{"gross_charge":null,"cash_price":null,"negotiated":{"min":6922.47,"median":7753.165,"max":24035.51},"posted_spread":{"n_items":0,"gross_min":null,"gross_max":null,"cash_min":null,"cash_max":null},"descriptions":["NSL/SINS NDSC MED&INF DCMPRN","NASAL/SINUS NDSC SURG MEDIAL&INF ORB WALL DCMPRN"],"inpatient_fallback":false,"medicare":{"amount":7089.62,"basis":"opps"},"multiples":{"cash_vs_medicare":null,"gross_vs_medicare":null}},"baylor_bumc":{"gross_charge":null,"cash_price":null,"negotiated":{"min":5369.0,"median":6572.4,"max":18388.42},"posted_spread":{"n_items":0,"gross_min":null,"gross_max":null,"cash_min":null,"cash_max":null},"descriptions":["NASAL/SINUS ENDOSCOPY, SURGICAL, WITH ORBITAL DECOMPRESSION; MEDIAL AND INFERIOR WALL"],"inpatient_fallback":false,"medicare":{"amount":7089.62,"basis":"opps"},"multiples":{"cash_vs_medicare":null,"gross_vs_medicare":null}},"medical_city_dallas":{"gross_charge":null,"cash_price":null,"negotiated":{"min":2369.0,"median":7125.07,"max":25655.0},"posted_spread":{"n_items":0,"gross_min":null,"gross_max":null,"cash_min":null,"cash_max":null},"descriptions":["Nasal/sinus endoscopy, surgical, with orbital decompression; medial and inferior wall"],"inpatient_fallback":false,"medicare":{"amount":7089.62,"basis":"opps"},"multiples":{"cash_vs_medicare":null,"gross_vs_medicare":null}},"thr_harris_methodist_fw":{"gross_charge":null,"cash_price":null,"negotiated":{"min":6838.53,"median":7612.0,"max":45459.65},"posted_spread":{"n_items":0,"gross_min":null,"gross_max":null,"cash_min":null,"cash_max":null},"descriptions":["NSL/SINS NDSC MED&INF DCMPRN"],"inpatient_fallback":false,"medicare":{"amount":7089.62,"basis":"opps"},"multiples":{"cash_vs_medicare":null,"gross_vs_medicare":null}},"ivinson_laramie":{"gross_charge":null,"cash_price":null,"negotiated":{"min":6922.47,"median":6922.47,"max":6922.47},"posted_spread":{"n_items":0,"gross_min":null,"gross_max":null,"cash_min":null,"cash_max":null},"descriptions":["NSL/SINS NDSC MED&INF DCMPRN"],"inpatient_fallback":false,"medicare":{"amount":7210.32,"basis":"opps"},"multiples":{"cash_vs_medicare":null,"gross_vs_medicare":null}},"regional_west_scottsbluff":{"gross_charge":null,"cash_price":null,"negotiated":{"min":7328.43,"median":7694.85,"max":10992.64},"posted_spread":{"n_items":0,"gross_min":null,"gross_max":null,"cash_min":null,"cash_max":null},"descriptions":["NSL/SINS NDSC MED&INF DCMPRN"],"inpatient_fallback":false,"medicare":{"amount":7328.43,"basis":"opps"},"multiples":{"cash_vs_medicare":null,"gross_vs_medicare":null}},"cheyenne_regional":{"gross_charge":null,"cash_price":null,"negotiated":{"min":7570.84,"median":7570.84,"max":7570.84},"posted_spread":{"n_items":0,"gross_min":null,"gross_max":null,"cash_min":null,"cash_max":null},"descriptions":["PR NASAL/SINUS NDSC SURG MEDIAL&INF ORB WALL DCMPRN","NSL/SINS NDSC MED&INF DCMPRN"],"inpatient_fallback":false,"medicare":{"amount":7210.32,"basis":"opps"},"multiples":{"cash_vs_medicare":null,"gross_vs_medicare":null}},"campbell_county_health":{"gross_charge":null,"cash_price":null,"negotiated":{"min":6230.22,"median":6230.22,"max":6230.22},"posted_spread":{"n_items":0,"gross_min":null,"gross_max":null,"cash_min":null,"cash_max":null},"descriptions":["NSL/SINS NDSC MED&INF DCMPRN"],"inpatient_fallback":false,"medicare":{"amount":7210.32,"basis":"opps"},"multiples":{"cash_vs_medicare":null,"gross_vs_medicare":null}},"crook_county_sundance":{"gross_charge":null,"cash_price":null,"negotiated":{"min":1509.0,"median":1509.0,"max":1509.0},"posted_spread":{"n_items":0,"gross_min":null,"gross_max":null,"cash_min":null,"cash_max":null},"descriptions":["Nasal/sinus endoscopy surg"],"inpatient_fallback":false,"medicare":{"amount":7210.32,"basis":"opps"},"multiples":{"cash_vs_medicare":null,"gross_vs_medicare":null}}}}