{"code":"82441","name":"CHLORINATED HYDROCARBONS SCREEN","name_source":"hospital_text","needs_curation":true,"code_class":"cpt_cat1","basis_kind":"clfs","medicare_national":6.01,"medicare_basis":"clfs","n_hospitals":9,"hospitals":{"utsw_clements":{"gross_charge":116.0,"cash_price":58.0,"negotiated":{"min":5.05,"median":26.24,"max":102.08},"posted_spread":{"n_items":1,"gross_min":116.0,"gross_max":116.0,"cash_min":58.0,"cash_max":58.0},"descriptions":["HCHG CHLORINATED HYDROCARBONS SCREEN","CHLORINATED HYDROCARBONS SCREEN","TEST FOR CHLOROHYDROCARBONS"],"inpatient_fallback":false,"medicare":{"amount":6.01,"basis":"clfs"},"multiples":{"cash_vs_medicare":9.7,"gross_vs_medicare":19.3}},"medical_city_dallas":{"gross_charge":null,"cash_price":null,"negotiated":{"min":3.61,"median":6.31,"max":66.77},"posted_spread":{"n_items":0,"gross_min":null,"gross_max":null,"cash_min":null,"cash_max":null},"descriptions":["Chlorinated hydrocarbons, screen","Chlorinated hydrocarbons, screen Age Under 21","Chlorinated hydrocarbons, screen Age 21+","Chlorinated hydrocarbons, screen Other Outpatient"],"inpatient_fallback":false,"medicare":{"amount":6.01,"basis":"clfs"},"multiples":{"cash_vs_medicare":null,"gross_vs_medicare":null}},"thr_harris_methodist_fw":{"gross_charge":null,"cash_price":null,"negotiated":{"min":5.05,"median":6.13,"max":11.78},"posted_spread":{"n_items":0,"gross_min":null,"gross_max":null,"cash_min":null,"cash_max":null},"descriptions":["TEST FOR CHLOROHYDROCARBONS"],"inpatient_fallback":false,"medicare":{"amount":6.01,"basis":"clfs"},"multiples":{"cash_vs_medicare":null,"gross_vs_medicare":null}},"ivinson_laramie":{"gross_charge":null,"cash_price":null,"negotiated":{"min":6.01,"median":6.01,"max":6.01},"posted_spread":{"n_items":0,"gross_min":null,"gross_max":null,"cash_min":null,"cash_max":null},"descriptions":["TEST FOR CHLOROHYDROCARBONS"],"inpatient_fallback":false,"medicare":{"amount":6.01,"basis":"clfs"},"multiples":{"cash_vs_medicare":null,"gross_vs_medicare":null}},"regional_west_scottsbluff":{"gross_charge":null,"cash_price":null,"negotiated":{"min":6.01,"median":6.31,"max":9.02},"posted_spread":{"n_items":0,"gross_min":null,"gross_max":null,"cash_min":null,"cash_max":null},"descriptions":["TEST FOR CHLOROHYDROCARBONS"],"inpatient_fallback":false,"medicare":{"amount":6.01,"basis":"clfs"},"multiples":{"cash_vs_medicare":null,"gross_vs_medicare":null}},"cheyenne_regional":{"gross_charge":null,"cash_price":null,"negotiated":{"min":6.31,"median":9.02,"max":12.02},"posted_spread":{"n_items":0,"gross_min":null,"gross_max":null,"cash_min":null,"cash_max":null},"descriptions":["CHG CHLORINATED HYDROCARBONS SCREEN","TEST FOR CHLOROHYDROCARBONS"],"inpatient_fallback":false,"medicare":{"amount":6.01,"basis":"clfs"},"multiples":{"cash_vs_medicare":null,"gross_vs_medicare":null}},"campbell_county_health":{"gross_charge":null,"cash_price":null,"negotiated":{"min":5.41,"median":5.41,"max":5.41},"posted_spread":{"n_items":0,"gross_min":null,"gross_max":null,"cash_min":null,"cash_max":null},"descriptions":["TEST FOR CHLOROHYDROCARBONS"],"inpatient_fallback":false,"medicare":{"amount":6.01,"basis":"clfs"},"multiples":{"cash_vs_medicare":null,"gross_vs_medicare":null}},"aspen_mountain_rock_springs":{"gross_charge":107.9,"cash_price":null,"negotiated":{"min":6.01,"median":53.95,"max":107.9},"posted_spread":{"n_items":1,"gross_min":107.9,"gross_max":107.9,"cash_min":null,"cash_max":null},"descriptions":["TEST FOR CHLOROHYDROCARBONS"],"inpatient_fallback":false,"medicare":{"amount":6.01,"basis":"clfs"},"multiples":{"cash_vs_medicare":null,"gross_vs_medicare":18.0}},"crook_county_sundance":{"gross_charge":null,"cash_price":null,"negotiated":{"min":6.01,"median":6.01,"max":6.01},"posted_spread":{"n_items":0,"gross_min":null,"gross_max":null,"cash_min":null,"cash_max":null},"descriptions":["Test for chlorohydrocarbons"],"inpatient_fallback":false,"medicare":{"amount":6.01,"basis":"clfs"},"multiples":{"cash_vs_medicare":null,"gross_vs_medicare":null}}}}