{"code":"92938","name":"Percutaneous transluminal revascularization of or through coronary artery bypass graft (internal mammary, free arterial, venous), any combination of intracoronary stent, atherectomy and angioplasty, i","name_source":"hospital_text","needs_curation":true,"code_class":"cpt_cat1","basis_kind":"unavailable","medicare_national":null,"medicare_basis":"unavailable","n_hospitals":7,"hospitals":{"utsw_clements":{"gross_charge":26680.0,"cash_price":13340.0,"negotiated":{"min":3854.19,"median":14994.16,"max":31771.0},"posted_spread":{"n_items":1,"gross_min":26680.0,"gross_max":26680.0,"cash_min":13340.0,"cash_max":13340.0},"descriptions":["HCHG PCI GRAFT AND OR STENT ATHRECTOMY EA ADDL VESSEL","PRQ TRLUML CORONARY BYP GRFT REVASC ADDL VESSEL"],"inpatient_fallback":false,"medicare":null,"multiples":null},"baylor_bumc":{"gross_charge":25132.15,"cash_price":15079.29,"negotiated":{"min":3901.0,"median":15862.0,"max":18849.11},"posted_spread":{"n_items":6,"gross_min":25132.15,"gross_max":25132.15,"cash_min":15079.29,"cash_max":15079.29},"descriptions":["HC TRANSLUMNL REVASC - EA ADD BRNCH","HC REVASC BMS BYPASS GRAFT ADD LC","HC REVASC BMS BYPASS GRAFT ADD LD","HC REVASC BMS BYPASS GRAFT ADD LM","HC REVASC BMS BYPASS GRAFT ADD RC","HC REVASC BMS BYPASS GRAFT ADD RI"],"inpatient_fallback":false,"medicare":null,"multiples":null},"medical_city_dallas":{"gross_charge":32554.72,"cash_price":32554.72,"negotiated":{"min":2180.7,"median":13831.86,"max":46251.0},"posted_spread":{"n_items":6,"gross_min":31152.84,"gross_max":33956.6,"cash_min":31152.84,"cash_max":33956.6},"descriptions":["Percutaneous transluminal revascularization of or through coronary artery bypass graft (internal mammary, free arterial, venous), any combination of intracoronary stent, atherectomy and angioplasty, i","PTCA RVS GFT STNT ADL LD","PTCA RVS GFT STNT ADL RC","PTCA RVS GFT STNT ADL LC"],"inpatient_fallback":false,"medicare":null,"multiples":null},"thr_harris_methodist_fw":{"gross_charge":null,"cash_price":null,"negotiated":{"min":10576.0,"median":16982.0,"max":21607.0},"posted_spread":{"n_items":0,"gross_min":null,"gross_max":null,"cash_min":null,"cash_max":null},"descriptions":["Zero Dollar Incidentals","Outpatient Grouper Procedures","Outpatient Surgery Grouper"],"inpatient_fallback":false,"medicare":null,"multiples":null},"cheyenne_regional":{"gross_charge":null,"cash_price":null,"negotiated":{"min":null,"median":null,"max":null},"posted_spread":{"n_items":0,"gross_min":null,"gross_max":null,"cash_min":null,"cash_max":null},"descriptions":["Professional Services"],"inpatient_fallback":false,"medicare":null,"multiples":null},"banner_casper":{"gross_charge":8663.0,"cash_price":3638.46,"negotiated":{"min":2339.01,"median":8229.85,"max":26502.0},"posted_spread":{"n_items":1,"gross_min":8663.0,"gross_max":8663.0,"cash_min":3638.46,"cash_max":3638.46},"descriptions":["REVASC GRFT BYPASS COR VSL ADDL"],"inpatient_fallback":false,"medicare":null,"multiples":null},"campbell_county_health":{"gross_charge":null,"cash_price":null,"negotiated":{"min":null,"median":null,"max":null},"posted_spread":{"n_items":0,"gross_min":null,"gross_max":null,"cash_min":null,"cash_max":null},"descriptions":["Physician Fee Schedule"],"inpatient_fallback":false,"medicare":null,"multiples":null}}}