{"code":"93271","name":"External patient and, when performed, auto activated electrocardiographic rhythm derived event recording with symptom-related memory loop with remote download capability up to 30 days, 24-hour attende","name_source":"hospital_text","needs_curation":true,"code_class":"cpt_cat1","basis_kind":"opps","medicare_national":97.13,"medicare_basis":"opps","n_hospitals":13,"hospitals":{"utsw_clements":{"gross_charge":null,"cash_price":null,"negotiated":{"min":91.79,"median":99.13499999999999,"max":1056.15},"posted_spread":{"n_items":0,"gross_min":null,"gross_max":null,"cash_min":null,"cash_max":null},"descriptions":["ECG/MONITORING AND ANALYSIS","XTRNL PT ACTIVATED ECG REC DWNLD 30 DAYS"],"inpatient_fallback":false,"medicare":{"amount":95.5,"basis":"opps"},"multiples":{"cash_vs_medicare":null,"gross_vs_medicare":null}},"medical_city_dallas":{"gross_charge":null,"cash_price":null,"negotiated":{"min":401.44,"median":828.39,"max":1171.2},"posted_spread":{"n_items":0,"gross_min":null,"gross_max":null,"cash_min":null,"cash_max":null},"descriptions":["External patient and, when performed, auto activated electrocardiographic rhythm derived event recording with symptom-related memory loop with remote download capability up to 30 days, 24-hour attende"],"inpatient_fallback":false,"medicare":{"amount":95.5,"basis":"opps"},"multiples":{"cash_vs_medicare":null,"gross_vs_medicare":null}},"parkland":{"gross_charge":1464.0,"cash_price":585.6,"negotiated":{"min":107.16,"median":823.45,"max":1129.58},"posted_spread":{"n_items":1,"gross_min":1464.0,"gross_max":1464.0,"cash_min":585.6,"cash_max":585.6},"descriptions":["Electrocardiogram (ECG) up to 30 days continuous with symptom monitoring and transmission and analysis"],"inpatient_fallback":false,"medicare":{"amount":95.5,"basis":"opps"},"multiples":{"cash_vs_medicare":6.1,"gross_vs_medicare":15.3}},"thr_harris_methodist_fw":{"gross_charge":null,"cash_price":null,"negotiated":{"min":95.5,"median":100.28,"max":107.92},"posted_spread":{"n_items":0,"gross_min":null,"gross_max":null,"cash_min":null,"cash_max":null},"descriptions":["ECG/MONITORING AND ANALYSIS"],"inpatient_fallback":false,"medicare":{"amount":95.5,"basis":"opps"},"multiples":{"cash_vs_medicare":null,"gross_vs_medicare":null}},"ivinson_laramie":{"gross_charge":null,"cash_price":null,"negotiated":{"min":91.79,"median":91.79,"max":91.79},"posted_spread":{"n_items":0,"gross_min":null,"gross_max":null,"cash_min":null,"cash_max":null},"descriptions":["ECG/MONITORING AND ANALYSIS"],"inpatient_fallback":false,"medicare":{"amount":97.13,"basis":"opps"},"multiples":{"cash_vs_medicare":null,"gross_vs_medicare":null}},"regional_west_scottsbluff":{"gross_charge":null,"cash_price":null,"negotiated":{"min":98.72,"median":103.66,"max":148.08},"posted_spread":{"n_items":0,"gross_min":null,"gross_max":null,"cash_min":null,"cash_max":null},"descriptions":["ECG/MONITORING AND ANALYSIS"],"inpatient_fallback":false,"medicare":{"amount":98.72,"basis":"opps"},"multiples":{"cash_vs_medicare":null,"gross_vs_medicare":null}},"cheyenne_regional":{"gross_charge":null,"cash_price":null,"negotiated":{"min":101.99,"median":101.99,"max":101.99},"posted_spread":{"n_items":0,"gross_min":null,"gross_max":null,"cash_min":null,"cash_max":null},"descriptions":["PR XTRNL PT ACTIVATED ECG REC DWNLD 30 DAYS","ECG/MONITORING AND ANALYSIS"],"inpatient_fallback":false,"medicare":{"amount":97.13,"basis":"opps"},"multiples":{"cash_vs_medicare":null,"gross_vs_medicare":null}},"campbell_county_health":{"gross_charge":null,"cash_price":null,"negotiated":{"min":82.61,"median":82.61,"max":82.61},"posted_spread":{"n_items":0,"gross_min":null,"gross_max":null,"cash_min":null,"cash_max":null},"descriptions":["ECG/MONITORING AND ANALYSIS"],"inpatient_fallback":false,"medicare":{"amount":97.13,"basis":"opps"},"multiples":{"cash_vs_medicare":null,"gross_vs_medicare":null}},"sheridan_memorial":{"gross_charge":2072.0,"cash_price":1657.6,"negotiated":{"min":104.03,"median":1864.8,"max":1968.4},"posted_spread":{"n_items":1,"gross_min":2072.0,"gross_max":2072.0,"cash_min":1657.6,"cash_max":1657.6},"descriptions":["Electrocardiogram (ECG) up to 30 days continuous with symptom monitoring and transmission and analysis"],"inpatient_fallback":false,"medicare":{"amount":97.13,"basis":"opps"},"multiples":{"cash_vs_medicare":17.1,"gross_vs_medicare":21.3}},"st_johns_jackson":{"gross_charge":469.0,"cash_price":469.0,"negotiated":{"min":137.52,"median":431.48,"max":459.62},"posted_spread":{"n_items":1,"gross_min":469.0,"gross_max":469.0,"cash_min":469.0,"cash_max":469.0},"descriptions":["Electrocardiogram (ECG) up to 30 days continuous with symptom monitoring and transmission and analysis"],"inpatient_fallback":false,"medicare":{"amount":97.13,"basis":"opps"},"multiples":{"cash_vs_medicare":4.8,"gross_vs_medicare":4.8}},"washakie_worland":{"gross_charge":653.0,"cash_price":564.19,"negotiated":{"min":313.44,"median":620.35,"max":639.94},"posted_spread":{"n_items":1,"gross_min":653.0,"gross_max":653.0,"cash_min":564.19,"cash_max":564.19},"descriptions":["EKG ANALYSIS EVENT REMOTE 0-30DAY"],"inpatient_fallback":false,"medicare":{"amount":97.13,"basis":"opps"},"multiples":{"cash_vs_medicare":5.8,"gross_vs_medicare":6.7}},"star_valley_afton":{"gross_charge":299.0,"cash_price":209.3,"negotiated":{"min":161.91,"median":285.54,"max":299.0},"posted_spread":{"n_items":1,"gross_min":299.0,"gross_max":299.0,"cash_min":209.3,"cash_max":209.3},"descriptions":["HC ECG/MONITORING AND ANALYSIS - CARDIAC EVENT MONITOR"],"inpatient_fallback":false,"medicare":{"amount":97.13,"basis":"opps"},"multiples":{"cash_vs_medicare":2.2,"gross_vs_medicare":3.1}},"evanston_regional_evanston":{"gross_charge":520.04,"cash_price":312.02,"negotiated":{"min":338.03,"median":434.23,"max":442.03},"posted_spread":{"n_items":1,"gross_min":520.04,"gross_max":520.04,"cash_min":312.02,"cash_max":312.02},"descriptions":["Electrocardiogram (ECG) up to 30 days continuous with symptom monitoring and transmission and analysis"],"inpatient_fallback":false,"medicare":{"amount":97.13,"basis":"opps"},"multiples":{"cash_vs_medicare":3.2,"gross_vs_medicare":5.4}}}}